[
    {
        "Name": "Margrit Pollak",
        "Birth": "1990-09-09T00:24:32.082Z",
        "Age": 34,
        "Gender": "female",
        "Email": "margrit.pollak@example.com",
        "Location": "Burg Stargard, Germany",
        "Phone": "0540-5791847"
    },
    {
        "Name": "Douglas Newman",
        "Birth": "1983-03-21T16:09:37.252Z",
        "Age": 42,
        "Gender": "male",
        "Email": "douglas.newman@example.com",
        "Location": "Skerries, Ireland",
        "Phone": "021-802-9925"
    },
    {
        "Name": "Aiden Martin",
        "Birth": "1949-07-24T09:40:19.173Z",
        "Age": 76,
        "Gender": "male",
        "Email": "aiden.martin@example.com",
        "Location": "Greymouth, New Zealand",
        "Phone": "(917)-173-3171"
    },
    {
        "Name": "Angelina Had\u017ei\u0107",
        "Birth": "1991-12-13T03:15:29.442Z",
        "Age": 33,
        "Gender": "female",
        "Email": "angelina.hadzic@example.com",
        "Location": "U\u017eice, Serbia",
        "Phone": "029-2585-252"
    },
    {
        "Name": "\u0633\u06cc\u0646\u0627 \u06a9\u0627\u0645\u0631\u0648\u0627",
        "Birth": "1966-11-19T22:17:41.762Z",
        "Age": 58,
        "Gender": "male",
        "Email": "syn.khmrw@example.com",
        "Location": "\u0627\u06cc\u0644\u0627\u0645, Iran",
        "Phone": "035-07337343"
    }
]